pip_sdk_test/__init__.py
pip_sdk_test/main.py
pip_sdk_test-1.0.dist-info/METADATA
pip_sdk_test-1.0.dist-info/WHEEL
pip_sdk_test-1.0.dist-info/entry_points.txt
pip_sdk_test-1.0.dist-info/top_level.txt
pip_sdk_test-1.0.dist-info/RECORD
