Metadata-Version: 2.1
Name: pip-sdk-test
Version: 1.0
Summary: A simple package that prints Hello, World!
Home-page: UNKNOWN
Author: Edgeble AI
Author-email: your.email@example.com
License: UNKNOWN
Platform: UNKNOWN
